aiobot/__init__.py
aiobot-0.1.0a1.dist-info/DESCRIPTION.rst
aiobot-0.1.0a1.dist-info/METADATA
aiobot-0.1.0a1.dist-info/RECORD
aiobot-0.1.0a1.dist-info/WHEEL
aiobot-0.1.0a1.dist-info/metadata.json
aiobot-0.1.0a1.dist-info/top_level.txt
